{
	"pageTitle": "Recherche de recette",
	"IngredientLabel": "Ingrédient",
	"IngredientSearchErrorMessage": "s'il vous plaît utiliser uniquement des alphabets",
	"RemoveLabel": "Retirer",
	"AddIngredientLabel": "Ajouter un nouvel ingrédient",
	"SearchLabel": "Chercher",
	"ReleavenceLabel": "Pertinence",
	"LowToHighLabel": "De bas en haut",
	"HighToLowLabel": "Haut en bas",
	"SeeMoreRecipesLabel": "Voir plus de recettes",
	"FilterLabel": "Filtre",
	"SortLabel": "Trier",
	"StoreAvailableLabel": "Disponible dans le Play Store et l'App Store",
	"CloseLabel": "Fermer",
	"FeatureUnAvailableMessage": "Caractéristique non disponible",
	"GoogleLoginLabel": "Connectez-vous avec Google",
	"FacebookLoginLabel": "Se connecter avec Facebook",
	"LoginLabel": "S'identifier",
	"PasswordLabel": "Mot de passe",
	"registerLabel": "registre",
	"signOutLabel": "Déconnexion",
	"FavoriteRecipeLabel": "Recettes préférées",
	"settingsLabel": "Paramètres"
}