{
	"pageTitle": "Busca de receitas",
	"IngredientLabel": "Ingrediente",
	"IngredientSearchErrorMessage": "use só alfabetos",
	"RemoveLabel": "Quitar",
	"AddIngredientLabel": "Engadir novo ingrediente",
	"SearchLabel": "Busca",
	"ReleavenceLabel": "Relevancia",
	"LowToHighLabel": "Baixo a alto",
	"HighToLowLabel": "Alto a baixo",
	"SeeMoreRecipesLabel": "Ver máis Receitas",
	"FilterLabel": "Filtro",
	"SortLabel": "Ordenar",
	"StoreAvailableLabel": "Dispoñible en Play Store e App Store",
	"CloseLabel": "Pechar",
	"FeatureUnAvailableMessage": "Característica non dispoñible",
	"GoogleLoginLabel": "Iniciar sesión con Google",
	"FacebookLoginLabel": "Iniciar sesión con Facebook",
	"LoginLabel": "Iniciar sesión",
	"PasswordLabel": "Contrasinal",
	"registerLabel": "Rexistrarse",
	"signOutLabel": "Saír",
	"FavoriteRecipeLabel": "Receitas favoritas",
	"settingsLabel": "Configuración"
}